{
  "name": "mbed-example-asynch-spi",
  "version": "0.0.4",
  "description": "Asynch SPI example",
  "private": true,
  "keywords": [
    "mbed",
    "cpputest",
    "spi"
  ],
  "author": "brendan.moran@arm.com",
  "licenses": [
    {
      "url": "https://spdx.org/licenses/Apache-2.0",
      "type": "Apache-2.0"
    }
  ],
  "extraIncludes": [],
  "dependencies": {
    "mbed": "ARMmbed/mbed-sdk-private",
    "mbed-cpputest": "ARMmbed/mbed-cpputest-private#~0.0.4"
  },
  "targetDependencies": {},
  "bin": "./source"
}